async_process_executor.py
async_process_executor-0.1.0.dist-info/LICENSE
async_process_executor-0.1.0.dist-info/METADATA
async_process_executor-0.1.0.dist-info/WHEEL
async_process_executor-0.1.0.dist-info/top_level.txt
async_process_executor-0.1.0.dist-info/RECORD
