Metadata-Version: 2.1
Name: async-process-executor
Version: 0.1.0
Summary: Run tasks in processes asynchronously
Home-page: https://github.com/turicas/async_process_executor/
Author: Álvaro Justen
Author-email: alvarojusten@gmail.com
License: UNKNOWN
Keywords: async parallel
Platform: UNKNOWN
Classifier: License :: OSI Approved :: GNU Lesser General Public License v3 or later (LGPLv3+)
Classifier: Natural Language :: English
Classifier: Operating System :: OS Independent
Classifier: Programming Language :: Python :: 3.7
